plyder/__init__.py
plyder/__version__.py
plyder/app.py
plyder/config.py
plyder/download_handlers.py
plyder/download_providers/__init__.py
plyder/download_providers/experimental/mega_restarts.sh
plyder/download_providers/mega.sh
plyder/downloader.py
plyder/main.py
plyder/metrics.py
plyder/routes/__init__.py
plyder/routes/server.py
plyder/static/__init__.py
plyder/static/axios.min.js
plyder/static/bootstrap.min.css
plyder/static/styles.css
plyder/templates/__init__.py
plyder/templates/index.html
plyder/utils.py
plyder-1.0.0.dist-info/LICENSE
plyder-1.0.0.dist-info/METADATA
plyder-1.0.0.dist-info/WHEEL
plyder-1.0.0.dist-info/entry_points.txt
plyder-1.0.0.dist-info/RECORD
