Metadata-Version: 2.1
Name: plyder
Version: 1.0.0
Summary: Download manager with web-interface.
Home-page: https://github.com/kpj/plyder
License: MIT
Author: kpj
Author-email: kim.philipp.jablonski@gmail.com
Requires-Python: >=3.9.0,<4.0.0
Classifier: License :: OSI Approved :: MIT License
Classifier: Programming Language :: Python :: 3
Classifier: Programming Language :: Python :: 3.9
Classifier: Programming Language :: Python :: 3.10
Classifier: Programming Language :: Python :: 3.11
Classifier: Programming Language :: Python :: 3.12
Requires-Dist: Jinja2 (>=2.11.3,<4.0.0)
Requires-Dist: PyYAML (>=5.4.1,<7.0.0)
Requires-Dist: aiofiles (>=0.6,<23.2)
Requires-Dist: appdirs (>=1.4.4,<2.0.0)
Requires-Dist: fastapi (>=0.104.0,<0.105.0)
Requires-Dist: humanize (>=3.3,<5.0)
Requires-Dist: jsonschema (>=3.2,<5.0)
Requires-Dist: loguru (>=0.5.3,<0.7.0)
Requires-Dist: mega.py (>=1.0.8,<2.0.0)
Requires-Dist: psutil (>=5.8.0,<6.0.0)
Requires-Dist: pydantic (>=2,<3)
Requires-Dist: sh (>=1.14.1,<3.0.0)
Requires-Dist: uvicorn (>=0.13.4,<0.22.0)
Project-URL: Repository, https://github.com/kpj/plyder
